neuron_assistant/__init__.py
neuron_assistant/assistant.py
neuron_assistant/config.json
neuron_assistant/config.sig
neuron_assistant/public_key.pem
neuron_assistant_v0_4-0.4.dist-info/METADATA
neuron_assistant_v0_4-0.4.dist-info/WHEEL
neuron_assistant_v0_4-0.4.dist-info/entry_points.txt
neuron_assistant_v0_4-0.4.dist-info/top_level.txt
neuron_assistant_v0_4-0.4.dist-info/RECORD
