Metadata-Version: 2.4
Name: neuron_assistant_v0.4
Version: 0.4
Summary: Neuron AI Assistant — auto GPU/CPU detection and local AI.
Home-page: https://github.com/yourusername/neuron-assistant
Author: Dev Patel
Author-email: your_email@example.com
Requires-Python: >=3.10
Requires-Dist: torch
Requires-Dist: transformers
Requires-Dist: huggingface-hub
Requires-Dist: cryptography
Requires-Dist: psutil
Dynamic: author
Dynamic: author-email
Dynamic: description
Dynamic: description-content-type
Dynamic: home-page
Dynamic: requires-dist
Dynamic: requires-python
Dynamic: summary
